.coveragerc
.hgignore
.hgtags
CHANGES.rst
COPYRIGHT.txt
LICENSE.txt
README.rst
bootstrap.py
buildout.cfg
pytest.ini
setup.py
tox.ini
src/gocept/__init__.py
src/gocept.zestreleaser.customupload.egg-info/PKG-INFO
src/gocept.zestreleaser.customupload.egg-info/SOURCES.txt
src/gocept.zestreleaser.customupload.egg-info/dependency_links.txt
src/gocept.zestreleaser.customupload.egg-info/entry_points.txt
src/gocept.zestreleaser.customupload.egg-info/namespace_packages.txt
src/gocept.zestreleaser.customupload.egg-info/not-zip-safe
src/gocept.zestreleaser.customupload.egg-info/requires.txt
src/gocept.zestreleaser.customupload.egg-info/top_level.txt
src/gocept/zestreleaser/__init__.py
src/gocept/zestreleaser/customupload/__init__.py
src/gocept/zestreleaser/customupload/doc.py
src/gocept/zestreleaser/customupload/upload.py
src/gocept/zestreleaser/customupload/tests/__init__.py
src/gocept/zestreleaser/customupload/tests/integration-doc.txt
src/gocept/zestreleaser/customupload/tests/integration.txt
src/gocept/zestreleaser/customupload/tests/test_destination.py
src/gocept/zestreleaser/customupload/tests/test_doctest.py
src/gocept/zestreleaser/customupload/tests/test_upload.py