Metadata-Version: 1.1
Name: gocept.zestreleaser.customupload
Version: 3.0
Summary: Plug-in for zest.releaser to allow uploading the created egg via SCP or SFTP to configurable destinations.
Home-page: https://bitbucket.org/gocept/gocept.zestreleaser.customupload
Author: gocept gmbh & co. kg
Author-email: mail@gocept.com
License: ZPL
Keywords: zest.releaser release upload custom PyPI SCP SFTP package sdist
Platform: UNKNOWN
Classifier: Development Status :: 5 - Production/Stable
Classifier: Environment :: Console
Classifier: Environment :: Plugins
Classifier: Intended Audience :: Developers
Classifier: License :: OSI Approved
Classifier: License :: OSI Approved :: Zope Public License
Classifier: Natural Language :: English
Classifier: Operating System :: OS Independent
Classifier: Programming Language :: Python :: 2
Classifier: Programming Language :: Python :: 2.7
Classifier: Programming Language :: Python :: 3
Classifier: Programming Language :: Python :: 3.4
Classifier: Programming Language :: Python :: 3.5
Classifier: Programming Language :: Python :: 3.6
Classifier: Programming Language :: Python :: Implementation
Classifier: Programming Language :: Python :: Implementation :: CPython
Classifier: Programming Language :: Python :: Implementation :: PyPy
Classifier: Topic :: Software Development
Classifier: Topic :: Software Development :: Libraries :: Python Modules
Classifier: Topic :: System :: Archiving :: Packaging
Classifier: Topic :: System :: Installation/Setup
Classifier: Topic :: Utilities
